agora_community_sdk/__init__.py
agora_community_sdk/agora.py
agora_community_sdk/frontend/.vscode/launch.json
agora_community_sdk/frontend/AgoraRTCSDK-2.6.1.js
agora_community_sdk/frontend/index.html
agora_community_sdk-0.1.10.dist-info/WHEEL
agora_community_sdk-0.1.10.dist-info/METADATA
agora_community_sdk-0.1.10.dist-info/RECORD
