Metadata-Version: 2.1
Name: agora-community-sdk
Version: 0.1.10
Summary: An SDK allowing the use of Agora SDK in python
Home-page: https://github.com/samyak-jain/AgoraPython
License: UNKNOWN
Author: samyak-jain
Author-email: samtan106@gmail.com
Requires-Python: >=3.6,<4.0
Classifier: Programming Language :: Python :: 3
Classifier: Programming Language :: Python :: 3.6
Classifier: Programming Language :: Python :: 3.7
Requires-Dist: nest_asyncio (>=1.0,<2.0)
Requires-Dist: pillow (>=6.0,<7.0)
Requires-Dist: pyppeteer (>=0.0.25,<0.0.26)
Requires-Dist: selenium (>=3.141,<4.0)
Requires-Dist: websockets (==6.0)
Project-URL: Repository, https://github.com/samyak-jain/AgoraPython
